javac_parser.py
javac_parser/__init__.py
javac_parser/__init__.pyi
javac_parser/__version__.py
javac_parser/javac_parser.py
javac_parser/javac_parser.pyi
javac_parser/lex-java-1.0-SNAPSHOT-jar-with-dependencies.jar
javac_parser/py.typed
javac_parser-1.0.0.dist-info/METADATA
javac_parser-1.0.0.dist-info/RECORD
javac_parser-1.0.0.dist-info/WHEEL
javac_parser-1.0.0.dist-info/top_level.txt
