Metadata-Version: 1.1
Name: javac_parser
Version: 1.0.0
Summary: Exposes the OpenJDK Java parser and scanner to Python
Home-page: https://github.com/naturalness/javac-parser
Author: Joshua Charles Campbell, Eddie Antonio Santos
Author-email: joshua2@ualberta.ca, easantos@ualberta.ca
License: AGPL3+
Keywords: java javac parser scanner lexer tokenizer
Platform: UNKNOWN
Classifier: License :: OSI Approved :: GNU Affero General Public License v3 or later (AGPLv3+)
Classifier: Programming Language :: Python :: 3
Classifier: Programming Language :: Python :: 2.7
Classifier: Programming Language :: Python :: 3.4
Classifier: Programming Language :: Python :: 3.5
Classifier: Programming Language :: Python :: 3.6
Classifier: Programming Language :: Python :: Implementation :: CPython
